tcs_garr/__init__.py
tcs_garr/chain/HARICA_TLS_ECC_Root_CA_2021.pem
tcs_garr/chain/HARICA_TLS_RSA_Root_CA_2021.pem
tcs_garr/commands/__init__.py
tcs_garr/commands/acme.py
tcs_garr/commands/approve.py
tcs_garr/commands/base.py
tcs_garr/commands/cancel.py
tcs_garr/commands/domains.py
tcs_garr/commands/download.py
tcs_garr/commands/init.py
tcs_garr/commands/k8s.py
tcs_garr/commands/list_certificates.py
tcs_garr/commands/request.py
tcs_garr/commands/revoke.py
tcs_garr/commands/smime.py
tcs_garr/commands/test_api.py
tcs_garr/commands/upgrade.py
tcs_garr/commands/validate.py
tcs_garr/commands/whoami.py
tcs_garr/exceptions.py
tcs_garr/harica_client.py
tcs_garr/logger.py
tcs_garr/main.py
tcs_garr/notifications.py
tcs_garr/settings.py
tcs_garr/utils.py
tcs_garr-0.25.1.dist-info/METADATA
tcs_garr-0.25.1.dist-info/WHEEL
tcs_garr-0.25.1.dist-info/entry_points.txt
tcs_garr-0.25.1.dist-info/licenses/LICENSE.md
tcs_garr-0.25.1.dist-info/RECORD
