Metadata-Version: 2.4
Name: tcs-garr
Version: 0.25.1
Summary: Command-line tool to manage and interact with Harica platform
License: GPL-3.0-or-later
License-File: LICENSE.md
Author: Consortium GARR
Author-email: system.support@garr.it
Maintainer: Consortium GARR
Maintainer-email: system.support@garr.it
Requires-Python: >=3.9
Classifier: License :: OSI Approved :: GNU General Public License v3 or later (GPLv3+)
Classifier: Programming Language :: Python :: 3
Classifier: Programming Language :: Python :: 3.10
Classifier: Programming Language :: Python :: 3.11
Classifier: Programming Language :: Python :: 3.12
Classifier: Programming Language :: Python :: 3.13
Classifier: Programming Language :: Python :: 3.14
Requires-Dist: beautifulsoup4 (>=4.13.4,<5.0.0)
Requires-Dist: colorama (>=0.4.6,<0.5.0)
Requires-Dist: cryptography (>=45.0.3,<46.0.0)
Requires-Dist: jwt (>=1.3.1,<2.0.0)
Requires-Dist: packaging (>=25.0,<26.0)
Requires-Dist: pyotp (>=2.9.0,<3.0.0)
Requires-Dist: python-dateutil (>=2.9.0.post0,<3.0.0)
Requires-Dist: pytz (>=2025.2,<2026.0)
Requires-Dist: requests (>=2.32.3,<3.0.0)
Requires-Dist: tabulate (>=0.9.0,<0.10.0)
Project-URL: Changelog, https://github.com/ConsortiumGARR/tcs-garr/blob/main/CHANGELOG.md
Project-URL: Documentation, https://github.com/ConsortiumGARR/tcs-garr/blob/main/README.md
Project-URL: Repository, https://github.com/ConsortiumGARR/tcs-garr
